mooquant_mootdx/__init__.py
mooquant_mootdx/barfeed.py
mooquant_mootdx/common.py
mooquant_mootdx/livefeed.py
mooquant_mootdx/tools.py
mooquant_mootdx-0.1.2.dist-info/METADATA
mooquant_mootdx-0.1.2.dist-info/RECORD
mooquant_mootdx-0.1.2.dist-info/WHEEL
mooquant_mootdx-0.1.2.dist-info/entry_points.txt
mooquant_mootdx-0.1.2.dist-info/top_level.txt
