Metadata-Version: 2.1
Name: mooquant-mootdx
Version: 0.1.2
Summary: mooquant mootdx module
Home-page: https://github.com/bopo/mooquant_mootdx
Author: bopo.wang
Author-email: ibopo@126.com
License: MIT license
Keywords: mooquant_mootdx
Platform: UNKNOWN
Classifier: Development Status :: 2 - Pre-Alpha
Classifier: Intended Audience :: Developers
Classifier: License :: OSI Approved :: MIT License
Classifier: Natural Language :: English
Classifier: Programming Language :: Python :: 3
Classifier: Programming Language :: Python :: 3.3
Classifier: Programming Language :: Python :: 3.4
Classifier: Programming Language :: Python :: 3.5
Requires-Dist: mooquant
Requires-Dist: mootdx
